llama_extract/__init__.py
llama_extract/extract.py
llama_extract/utils.py
llama_extract-0.1.1.dist-info/LICENSE
llama_extract-0.1.1.dist-info/METADATA
llama_extract-0.1.1.dist-info/WHEEL
llama_extract-0.1.1.dist-info/RECORD
