Metadata-Version: 2.3
Name: llama-extract
Version: 0.1.1
Summary: Structured data extraction from files.
License: MIT
Author: Logan Markewich
Author-email: logan@runllama.ai
Requires-Python: >=3.9,<4.0
Classifier: License :: OSI Approved :: MIT License
Classifier: Programming Language :: Python :: 3
Classifier: Programming Language :: Python :: 3.9
Classifier: Programming Language :: Python :: 3.10
Classifier: Programming Language :: Python :: 3.11
Classifier: Programming Language :: Python :: 3.12
Classifier: Programming Language :: Python :: 3.13
Requires-Dist: llama-cloud (==0.1.11)
Requires-Dist: llama-index-core (>=0.11.0,<0.12.0)
Requires-Dist: python-dotenv (>=1.0.1,<2.0.0)
